gefest_simple_rest_client/__init__.py
gefest_simple_rest_client/types_stubs.py
gefest_simple_rest_client/client/__init__.py
gefest_simple_rest_client/client/base.py
gefest_simple_rest_client/endpoint/__init__.py
gefest_simple_rest_client/endpoint/base.py
gefest_simple_rest_client/endpoint/path_template.py
gefest_simple_rest_client/errors/__init__.py
gefest_simple_rest_client/errors/path_params_errors.py
gefest_simple_rest_client/protocols/__init__.py
gefest_simple_rest_client/protocols/client.py
gefest_simple_rest_client-1.2025.3.16.dist-info/LICENSE
gefest_simple_rest_client-1.2025.3.16.dist-info/METADATA
gefest_simple_rest_client-1.2025.3.16.dist-info/WHEEL
gefest_simple_rest_client-1.2025.3.16.dist-info/top_level.txt
gefest_simple_rest_client-1.2025.3.16.dist-info/RECORD
