Metadata-Version: 2.2
Name: gefest_simple_rest_client
Version: 1.2025.3.16
Summary: Abstractions for create REST API client
Author-email: "Sergei (Gefest) Romanchuk" <pod.cargoes.0u@icloud.com>
License: MIT License
Project-URL: homepage, https://github.com/GefMar/gefest_simple_rest_client
Classifier: License :: OSI Approved :: MIT License
Requires-Python: >=3.12
License-File: LICENSE
Requires-Dist: httpx>=0.28.1
